bxypyutils/__init__.py
bxypyutils/converters.py
bxypyutils/email_tools.py
bxypyutils/formatters.py
bxypyutils/import_.py
bxypyutils/inplace.py
bxypyutils/installer.py
bxypyutils/json_plus.py
bxypyutils/logger.py
bxypyutils/regexp.py
bxypyutils/terminal.py
bxypyutils/testprint.py
bxypyutils/time.py
bxypyutils/zhchar.py
bxypyutils/zipfile_plus.py
bxypyutils-1.0.3.dist-info/LICENSE
bxypyutils-1.0.3.dist-info/METADATA
bxypyutils-1.0.3.dist-info/WHEEL
bxypyutils-1.0.3.dist-info/top_level.txt
bxypyutils-1.0.3.dist-info/RECORD
