Metadata-Version: 2.1
Name: bxypyutils
Version: 1.0.3
Summary: UNKNOWN
Home-page: https://github.com/bobdadada/bxypyutils
Author: Xingyu Bao
Author-email: baoxingyubob@outlook.com
License: UNKNOWN
Platform: UNKNOWN
Classifier: Programming Language :: Python :: 3
Classifier: License :: OSI Approved :: MIT License
Classifier: Operating System :: OS Independent
Requires-Dist: six
